cyberbrain/__init__.py
cyberbrain/basis.py
cyberbrain/block_stack.py
cyberbrain/frame.py
cyberbrain/frame_tree.py
cyberbrain/internal/_detect_computed_goto.py
cyberbrain/logger.py
cyberbrain/rpc_client.py
cyberbrain/tracer.py
cyberbrain/utils.py
cyberbrain/value_stack.py
cyberbrain-0.2.3.dist-info/WHEEL
cyberbrain-0.2.3.dist-info/METADATA
cyberbrain-0.2.3.dist-info/LICENSE
cyberbrain-0.2.3.dist-info/RECORD
