Metadata-Version: 2.1
Name: cyberbrain
Version: 0.2.3
Summary: Python debugging, redefined.
License: MIT
Keywords: debugging,debugger,visualization
Author-email: laike9m <laike9m@gmail.com>
Requires-Python: >=3.7,<3.10
Classifier: License :: OSI Approved :: MIT License
Classifier: Programming Language :: Python :: 3
Classifier: Programming Language :: Python :: 3.7
Classifier: Programming Language :: Python :: 3.8
Classifier: Programming Language :: Python :: 3.9
Requires-Dist: attrs<21.0.0,>=20.0.0
Requires-Dist: cheap-repr<1.0.0,>=0.4.2
Requires-Dist: crayons<1.0.0,>=0.3.0
Requires-Dist: get-port<1.0.0,>=0.0.5
Requires-Dist: jsonpickle<2.0.0,>=1.4.1
Requires-Dist: more-itertools<9.0.0,>=8.5.0
Requires-Dist: msgpack<2.0.0,>=1.0.2
Requires-Dist: portpicker<2.0.0,>=1.3.1
Requires-Dist: pygments<3.0.0,>=2.6.1
Requires-Dist: requests<3.0.0,>=2.25.1
Requires-Dist: shortuuid<2.0.0,>=1.0.1
Requires-Dist: typing-extensions<4.0.0,>=3.7.4
Requires-Dist: ujson==4.1.0
Provides-Extra: extra_tests
Requires-Dist: numpy==1.18; extra == "extra_tests"
Requires-Dist: pandas==1.1.3; extra == "extra_tests"
Project-URL: Bug Tracker, https://github.com/laike9m/Cyberbrain/issues
Project-URL: Funding, https://github.com/sponsors/laike9m
Project-URL: homepage, https://github.com/laike9m/Cyberbrain
Project-URL: repository, https://github.com/laike9m/Cyberbrain
